Workbook

Sheet Fichamento
A1: # | B1: Referência (citação) | C1: Arquivo | D1: Tipo | E1: Revisado por pares? | F1: Eixo | G1: Papel no artigo | H1: Objetivo (resumo) | I1: Dados e período | J1: Método | K1: Principais resultados (com página) | L1: Veredito sobre o uso no artigo | M1: Parâmetro que fornece | N1: Ressalvas para o uso | O1: Citação direta útil | P1: Versão lida / paginação | Q1: Revisado por (assinatura)
A2: 1 | B2: BAUR; LUCEY (2009) | C2: baur-2009.md | D2: Periódico | E2: Sim | F2: 1 | G2: P1 | H2: Definir e testar flight-to-quality, flight-from-quality e contágio entre ações e títulos soberanos em crises (p. 339-340). | I2: 8 países desenvolvidos (EUA incl.), MSCI ações e títulos 10+ anos, diário, moeda local, jan/1994-set/2006 (T = 3.291); 6 crises definidas por evento (p. 344-346). Sem emergentes. | J2: DCC-GARCH(1,1) + regressão do retorno do título sobre ações com dummies de crise (janela de 20 pregões; referência de 70 dias); painel GARCH; robustez com janelas de 5 a 50 pregões e Monte Carlo (p. 342-351). | K2: EUA: flight-to-quality em só 2 de 6 crises (Hong Kong 1997: -0,3856; Rússia 1998: -0,4641); contágio no 11/set (+0,2732) (Tab. 4a, p. 348; Tab. 5, p. 350). Correlação incondicional EUA -0,0149 (Tab. 2, p. 344). Fugas 'die out rather fast': janelas > 20 pregões tiram a significância (p. 351). | L2: P1: SUSTENTA EM PARTE (flight-to-quality nos EUA em 2 de 6 crises). 'Treasury como principal destino': NÃO SUSTENTA diretamente. | M2: Definição de flight-to-quality: queda significativa da correlação E nível negativo (senão é só 'decoupling') (p. 341). Janela de crise de 20 pregões; datas de crises 1997-2002 (p. 346). | N2: Crises por evento (não VIX/drawdown); DCC e dummies, não correlação móvel de 63 dias; amostra 1994-2006; janela longa pode diluir fugas curtas. Inconsistência interna texto x Tab. 5 sobre o 11/set. | O2: "If the co-movement of stocks and bonds turns negative in crisis periods, investors that hold both stocks and bonds will suffer less..." (p. 340) | P2: Versão publicada (PDF no site de Lucey), p. 339-352.
A3: 2 | B3: BAELE et al. (2020) | C3: baele-2020.md | D3: Periódico | E3: Sim | F3: 1 | G3: P1; contexto P3 | H3: Definir e identificar dias de flight to safety (FTS) em 23 países só com retornos de ações e do título de referência; consequências para fluxos, emergentes e hedge (p. 690-691). | I3: 23 países desenvolvidos, ações (Datastream) e título de 10 anos, diário, moeda local, jan/1980-jun/2015 (p. 696). Seção de emergentes: 25 bolsas (Brasil incl.) e EMBI em dólar (p. 728-729). | J3: Três modelos (regime-switching bivariado; limiar tipo exceedance; índice ordinal) combinados por Bernoulli multivariada; FTS se prob. conjunta > 50% (p. 695-709). Kernels de 360 e 7 dias. | K3: FTS em 1,74% dos dias (EUA 2,27%); ações -2,29% e títulos +0,43% em dias de FTS (Tab. 6, p. 711). Correlação -58,5% em FTS vs -4,18% fora (p. 702-703). 62% dos episódios duram 1 dia (p. 713). Só 21,6% dos FTS coincidem com alta volatilidade (p. 710). Soberanos emergentes em dólar com betas de FTS negativos, signif. em no máx. 7 de 24 países: ativos de risco (p. 731). | L3: P1: SUSTENTA para dias de FTS em desenvolvidos. 'Treasury como principal destino': SUSTENTA EM PARTE (autores chamam de 'problematic', p. 726). P3: apoio conceitual (EMBI em dólar, FTS global). | M3: Definição de FTS em 3 critérios (p. 690); FTS global = FTS dos EUA como proxy (p. 727); razão de volatilidade curto/longo de 1,72 como limiar de estresse (p. 707). | N3: Correlação negativa é parte da definição de FTS (resultado em parte construído); episódios de poucos dias x janela de 63 dias; crise por VIX > 30 não equivale a FTS. Evidência de emergentes é EMBI em dólar, não NTN-B. | O3: "These sovereign bonds cannot function as a 'safe asset' for these emerging markets due to default and exchange rate risks" (p. 726) | P3: WP NBER 19095 (mai/2019) conferido na versão RFS; paginação da RFS.
A4: 3 | B4: CONNOLLY; STIVERS; SUN (2005) | C4: connolly-2005.md | D4: Periódico | E4: Sim | F4: 1 | G4: P2 | H4: Verificar se incerteza do mercado acionário (VIX, turnover) prevê a correlação futura ações x Treasury e se associa à relação contemporânea (p. 2-3). | I4: EUA, diário, 1986-2000 (3.755 obs.); CRSP e Treasury de 10 anos (retornos a partir de yields); VIX antigo (S&P 100, hoje VXO) (p. 10-11). Apêndices: Alemanha e G-7. | J4: Correlação futura de 22 pregões condicionada ao VIX em t-1; regressão B = a0 + (a1 + a2 ln VIX + a3 CV)·S com Newey-West (5 lags); modelo de regimes com transição dependente do VIX (p. 16-28). | K4: Correlação média 0,340 (todos os dias) vs 0,079 com VIX > 30 e 0,062 com VIX > 40 (Tab. 2, p. 40). a2 = -0,208 (t = -4,33) em 1986-2000; -0,513 em 1993-2000 (Tab. 3, p. 41). Regime de alta incerteza: correlação ≈ -0,20 vs 0,52 no normal (p. 26). Padrão se repete na Alemanha e quase todo o G-7 (p. 32-34). | L4: P2 (EUA): SUSTENTA (CONFIRMADO). Parte 'não se espera no Brasil' é hipótese própria do artigo, não testada aqui. | M4: Limiares VIX 20/25/30/35/40 (Tab. 2, p. 40); horizonte de 22 pregões; especificação a2 < 0 para testar P2 (Eq. 5, p. 18); datas das crises asiática e russa (p. 19). | N4: 'Decrescente' ≠ 'negativa': média segue positiva com VIX > 30. VIX antigo (S&P 100). Amostra de inflação baixa e estável (limita 2022). Páginas do manuscrito de 2003, não do JFQA. | O4: "we find a negative relation between the uncertainty measures and the future correlation of stock and bond returns." (resumo, p. 161) | P4: Preprint aceito (UNC, 20/06/2003); paginação do manuscrito. Versão JFQA não acessada.
A5: 4 | B5: CAMPBELL; SUNDERAM; VICEIRA (2017) | C5: campbell-2017.md | D5: Periódico | E5: Sim | F5: 2 | G5: Contexto P1/P2; exploratória 2022 | H5: Documentar que a covariância Treasury x ações nos EUA muda de magnitude e sinal e modelar a estrutura a termo com essa troca de sinal (p. 264). | I5: EUA, trimestral 1953T1-2014T4, com segundos momentos realizados a partir de dados diários; títulos zero cupom (até 10 anos), TIPS desde 1999, CRSP (p. 275-277). | J5: Covariância e beta realizados em janela de 3 meses de dados diários; VAR (janela de 20 trimestres); modelo de estrutura a termo linear-quadrático com filtro de Kalman unscented (p. 265-275). | K5: Beta do Treasury ≈ 0,4 nos anos 1980 e ≈ -0,2 nos anos 2000, com troca de sinal (p. 265-266). Covariância com choques de deflação acompanha a covariância ações x títulos (p. 267). Títulos viram hedges melhores em tempos ruins (corr. 0,69 entre choques, p. 282). Prêmio a termo de 1,17% (1980) a -0,79% (2008) (p. 288). | L5: Frase da introdução sobre 'natureza do choque': SUSTENTA EM PARTE (explica pelo regime macro/inflação, não pelo tipo de choque nem por aversão a risco). Sugere redação mais fiel na ficha. | M5: Janela de 3 meses (22 pregões/mês, 264/ano) respalda 63 dias (nota 10, p. 277); fórmula de retorno a partir de yield; beta = cov/var das ações (p. 265). | N5: Trabalha com covariância e beta, não correlação; preço do risco constante; ligação com choques de oferta é conjectura da conclusão (p. 297). | O5: "since the turn of the century and particularly during these downturns, Treasury bond returns have been negatively correlated with stock returns at a daily frequency." (p. 264) | P5: Versão publicada (CFR), p. 263-301.
A6: 5 | B6: FORBES; RIGOBON (2002) | C6: forbes-2002.md | D6: Periódico | E6: Sim | F6: 2 | G6: Método (viés de volatilidade) | H6: Mostrar que testes de contágio baseados em aumento de correlação são viesados pela heterocedasticidade e propor ajuste (p. 2223-2226). | I6: Índices diários de ações (Datastream, US$), 28 mercados (Brasil incl.) nas crises de 1997 e 1994; 10 mercados em 1987 (p. 2236-2249). Só ações. | J6: Correlações condicionais e ajustadas a partir de VAR bivariado com retornos de 2 dias e 5 lags; teste t unilateral, crítico 1,65 (p. 2236-2239). | K6: Exemplo: correlação sobe de 10% para 71% só pela variância (Tab. I, p. 2230). Ásia 1997: contágio em 15 países sem ajuste, só Itália com ajuste (p. 2239-2242). México 1994, Brasil: 0,791 → 0,390 ajustada (Tab. VI-VII, p. 2246-2247). 'No contagion, only interdependence' (p. 2250). | L6: Pendência do plano (ajustar ou discutir como limitação): SUSTENTA o viés e fornece a fórmula. Usar como robustez + limitação. | M6: ρ = ρ* / √(1 + δ[1 - ρ*²]), δ = σ²alta/σ²baixa - 1 (Eq. 10-11, p. 2233); x = retorno das ações como fonte da variância. | N6: Hipóteses (sem choques globais omitidos e sem retroalimentação, p. 2234) pouco plausíveis em crises de VIX; o ajuste altera a magnitude, não o sinal (inferência do grupo pela Eq. 9). | O6: "This paper shows that correlation coefficients are conditional on market volatility." (p. 2223) | P6: Versão publicada (JSTOR), p. 2223-2261; NBER WP 7267 para conferir fórmulas.
A7: 6 | B7: MOLENAAR et al. (2024) | C7: molenaar-2024.md | D7: Periódico | E7: Sim | F7: 2 | G7: P3 e contraste EUA x Brasil; contexto P1 | H7: Explicar com variáveis econômicas quando a correlação ações x títulos fica acima ou abaixo de zero e o efeito em carteiras (p. 18). | I7: Mensal; EUA desde 1875, RU desde 1801, França desde 1871; G7 desde 1988; 5 emergentes, Brasil desde jan/2002 (títulos JGEMBBR, moeda local) (Tab. 3, p. 25; Tab. A3, p. 32). | J7: Correlação de Spearman em janelas de 36 meses regredida em inflação e juro real (modelos empírico e teórico), Newey-West 35 lags (p. 20-27). | K7: EUA: correlação 0,35 (1970-99) vs -0,29 (2000-23); 60/40 com vol. de 10,5% → 8,4% (p. 17; Tab. 5, p. 28). EUA 1961-2023: R² aj. 0,52 a 0,79 (Tab. 2, p. 23). Brasil: R² aj. 0,01, menor da tabela (Tab. 3, p. 25). Países com títulos mais arriscados têm correlação mais positiva (p. 30). | L7: Brasil com baixo poder explicativo dos fatores macro: SUSTENTA. Fonte para quedas simultâneas em 2022: NÃO SUSTENTA (buscar outra). Natureza do choque: SUSTENTA EM PARTE (revisão teórica, p. 20). | M7: Janelas de 21 ou 63 obs. com dados diários (p. 33) → respalda 63 dias; Spearman como robustez; Fisher dispensável para |ρ| ≤ 0,75 (nota 25, p. 35). | N7: Mensal/36 meses (não diário/63 dias); Spearman; título brasileiro é JGEMBBR, não NTN-B; não separa crises nem usa VIX. | O7: "For countries where government bonds are considered riskier, stock–bond correlations tend to be more positive..." (p. 30) | P7: Versão publicada (FAJ, acesso aberto), p. 17-36.
A8: 7 | B8: DUFOUR; STANCU; VAROTTO (2017) | C8: dufour-2017.md | D8: Periódico | E8: Sim | F8: 3 | G8: P3 (analogia); base parcial P4 | H8: Mostrar que o sinal da co-movimentação ações x títulos soberanos da zona do euro depende do nível de risco de crédito soberano (p. 2-5). | I8: 11 países da zona do euro (baixo, médio e alto risco); 562 títulos MTS, diário, out/2004-dez/2013; CDS 5 anos; subperíodos pré-crise, subprime, soberana I e II (p. 8-10). | J8: Painel com efeitos fixos (excesso de retorno do título sobre ações, ΔCDS, Δbid-ask), fator de crédito ortogonalizado; beta variável com dummy de CDS > limiar; correlação móvel de 1 ano (p. 6-13). | K8: Beta de ações dos países de alto risco: -0,039 (subprime) → +0,096 e +0,171 (soberana I e II); baixo risco sempre negativo (Tab. III, p. 31). Troca de sinal quando CDS 5 anos > 2% (p. 13). Correlação títulos x ações alto risco: -28,4% → +45,0% (Tab. V, p. 34). | L8: 'Títulos de alto risco perderam status de ativo seguro': SUSTENTA (p. 22). Título doméstico carrega risco-país: SUSTENTA EM PARTE. Base da P4 (local x global): NÃO SUSTENTA diretamente; só evidência indireta (subprime x crise soberana). | M8: Limiar CDS 5 anos > 2% (testado de 1% a 3%) (p. 13, nota 13); dummy de FTS: título > +2 dp e ações < -2 dp (p. 18); janela de 1 ano; winsorização 1%-99%. | N8: Zona do euro (moeda comum, sem risco cambial); Brasil fora da amostra; mede betas de painel, não correlação de 63 dias. Sugere reformular P4 em termos de risco soberano elevado. | O8: "government bonds of high risk countries lost their 'safe-asset' status during the recent sovereign debt crisis" (p. 22) | P8: Manuscrito aceito (CentAUR), p. 1-48; paginação do periódico (p. 25-46) não acessada.
A9: 8 | B9: HOFMANN; SHIM; SHIN (2020) | C9: hofmann-2020.md | D9: Periódico | E9: Sim | F9: 3 | G9: P3 (controle pelo câmbio) | H9: Examinar como o prêmio de risco de crédito de títulos soberanos em moeda local de emergentes varia com o câmbio (p. 1, 4-5). | I9: 14 emergentes (Brasil incl.), diário, jan/2005-dez/2017 (~3.300 dias), títulos de 5 anos em moeda local, EMBI, swap cambial, VIX (p. 10-12; Apêndice, p. 27). | J9: Modelo teórico de carteira; choques cambiais identificados em dias de notícias do BCE; projeções locais em painel (1 a 50 dias) com controle de VIX e juros (p. 7-14). | K9: Apreciação de 1% contra o dólar reduz spread local e prêmio de crédito em ~10 p.b. e o spread em moeda estrangeira em ~15 p.b. (p. 14; Fig. 3, p. 15). Câmbio relevante é o bilateral contra o dólar, não o efetivo (p. 16-18). Depreciação e risco de crédito andam juntos (p. 23). | L9: Mecanismo depreciação → saída de estrangeiros → alta de spreads: SUSTENTA. Controle por USD/BRL na P3: SUSTENTA. Título doméstico como não-refúgio: SUSTENTA EM PARTE. | M9: Usar câmbio bilateral USD/BRL (não efetivo) (p. 5, 22); prêmio de Du e Schreger; variação % do VIX como controle (p. 13-14). | N9: Não trata de ações nem de crises; títulos nominais de 5 anos, não indexados (NTN-B); painel sem estimativa só do Brasil. Atenção à convenção do câmbio (alta = apreciação no artigo). Controlar pelo câmbio pode absorver parte do efeito de risco-país. | O9: "our findings show that currency depreciation and rising credit risk go hand in hand." (p. 23) | P9: BIS WP 775 (rev. ago/2020), p. 1-27; versão JMCB não acessada.
A10: 9 | B10: BIANCONI; YOSHINO; MACHADO DE SOUSA (2013) | C10: bianconi-2013.md | D10: Periódico | E10: Sim | F10: 4 | G10: Contexto/lacuna | H10: Medir a transmissão do estresse dos EUA em 2008 para ações e títulos dos BRIC (p. 77, 107-108). | I10: BRIC; ações diárias 2003-2010; títulos = EMBI JPMorgan em dólar 2005-2010 (1.364 obs. conjuntas); estresse dos EUA = z(VIX) + z(TED) (p. 80-85). | J10: Heat maps de volatilidade, VAR, Johansen/VECM e DCC-GARCH t-Student (p. 81-101). | K10: Correlação ações x 'retornos' do EMBI no Brasil -0,486*** (Tab. 15, p. 106). Estresse EUA x ações Brasil -0,462; x EMBI Brasil 0,455 (Tab. 5 e 10). Correlações DCC sobem após o Lehman (p. 102, 107). | L10: Contexto eixo 4: SUSTENTA que usam EMBI em dólar, não título doméstico. NÃO usar o sinal como evidência a favor ou contra P3 (EMBI tratado ora como taxa, ora como retorno). | M10: Medida de estresse z(VIX) + z(TED) (p. 85); índice de calor com média móvel de 30 dias (nota 14, p. 81); marco do Lehman (set/2008). | N10: Ambiguidade taxa x índice inverte o sinal; amostra curta de títulos; uma única crise externa. | O10: "Stock and bond return correlations for Brazil and Russia are significantly large and negative." (p. 76) | P10: Versão publicada (site do autor, Tufts), p. 76-109.
A11: 10 | B11: CARDOSO; GARCIA (2023) | C11: cardoso-2023.md | D11: Anais | E11: Não (anais) | F11: 4 | G11: Contexto/lacuna; apoio indireto P3 | H11: Estudar o comovimento títulos x ações no Brasil (beta) e seus determinantes macro, de risco e de fluxos, comparando com a literatura dos EUA (p. 1-2, 15). | I11: Brasil, retornos anuais em frequência mensal, a partir de jan/2006; IDkA Pré 5 anos (principal) e IDkA IPCA 5 anos (comparação); Ibovespa; IPCA, IBC-Br, CDS, EMBI, câmbio, fluxos (p. 2-13). | J11: MQO móvel com janela de 36 meses e Newey-West 18 lags; regressão dos betas na correlação IPCA x hiato; correlação canônica (p. 3-15). Sem crises, sem VIX, sem dados diários. | K11: Beta títulos x ações muito positivo de 2015 ao início de 2020; não significativo antes e depois (p. 3). Correlação IPCA x hiato explica o beta (coef. -0,7259; R² 0,527) (Tab. 1, p. 6). CDS explica Ibovespa (R² 0,713) e títulos (R² 0,335) (Tab. 2, p. 6). NTN-B com padrão 'very similar' ao prefixado (p. 10). | L11: Afirmação da introdução (comovimento positivo 2015-2020, horizonte anual, sem crises): SUSTENTA. 'Usaram IDkA IPCA': SUSTENTA EM PARTE (série secundária). Ameaça à lacuna: NÃO. | M11: IDkA IPCA 5 anos desde jan/2006 (p. 2, 9); excesso de retorno sobre LTN 12 meses; janela de 36 meses + Newey-West 18 lags (p. 3). | N11: Não publicado em periódico (versão revista no 24º EBFin 2024, lida só parcialmente). Mede beta, não correlação. Os EUA não são estimados. | O11: "From 2015 to beginning of 2020, the series are highly positively correlated." (p. 3) | P11: Anais 45º EBE (16 p., jul/2023); páginas do PDF.
A12: 11 | B12: SILVA; BERTELLA; PEREIRA (2014) | C12: silva-2014.md | D12: Periódico | E12: Sim | F12: 4 | G12: Contexto (Ibovespa x EMBI-BR) | H12: Verificar se variáveis macro domésticas e externas explicam o Ibovespa no longo e no curto prazo, e se o precedem (p. 317, 319). | I12: Brasil, mensal, jan/1995-dez/2007 (156 obs.); Ibovespa, produção, IPCA, Selic real, EMBI-BR, câmbio real, S&P 500, fed funds, petróleo (p. 324-326). Sem título doméstico. | J12: Raiz unitária, VAR(4), Johansen/VECM, dummy de ago/1998, Granger e resposta ao impulso (p. 322-333). | K12: Um vetor de cointegração (traço 171,97) (Tab. 5, p. 330). Longo prazo: Ibovespa positivo com S&P 500 e petróleo e negativo com EMBI-BR (Tab. 7, p. 331). S&P 500 e petróleo antecedem o Ibovespa; EMBI-BR não (Tab. 8, p. 332). Choque de risco de crédito é o de maior efeito negativo (p. 332-333). | L12: Afirmação antiga 'tratam o Brasil de forma indireta': NÃO SUSTENTA. Reformular: estudam o Ibovespa e o risco-país (EMBI-BR), sem títulos domésticos. Ameaça à lacuna: NÃO. | M12: EMBI-BR como proxy de risco-país (p. 326); dummy de pulso para ago/1998 (p. 330). | N12: Não estima correlação ações x títulos; dados mensais; amostra exclui 2008. Coautor correto: Mario Augusto Bertella. | O12: "o risco de crédito, medido pelo EMBI-BR, mostrou-se também significante e inversamente relacionado" (p. 333) | P12: Versão publicada (SciELO), p. 317-336.
A13: 12 | B13: MARTÍNEZ ARROYO; MARÍN RODRÍGUEZ (2021) | C13: martinez-arroyo-2021.md | D13: Periódico | E13: Sim | F13: 4 | G13: Contexto (CDS x título) | H13: Analisar a relação entre CDS, risco soberano e dívida pública no Brasil, Chile, Colômbia e México, 2010-2019 (p. 583, 587). | I13: 4 países latino-americanos; títulos de 10 anos e CDS 5 anos, diário, 12/04/2010-22/02/2019 (2.315 obs.), Bloomberg (p. 597-598). Sem ações. | J13: Dickey-Fuller, causalidade de Granger e DCC-GARCH bivariado título x CDS (p. 594-604). | K13: Brasil: Granger bidirecional (títulos → CDS F = 10,35; CDS → títulos F = 24,13) (Tab. 1, p. 600). DCC muito persistente (a = 0,0421; b = 0,9476) (Tab. 4, p. 603). Correlação título x CDS decrescente nos últimos anos (p. 604-605). | L13: Uso para comovimento ações x títulos na América Latina: NÃO SUSTENTA. Serve só para 'títulos soberanos respondem ao risco de crédito (CDS)'. Ameaça à lacuna: NÃO. | M13: CDS como proxy de risco soberano (p. 585); preenchimento de feriados com o último valor (p. 597). | N13: Não trata de ações nem usa wavelets; moeda dos títulos não informada (provavelmente dívida externa); série de 'preços' do Brasil parece taxa e tem zeros (Tab. 2, p. 601). | O13: "para Brasil y Colombia, existe una causalidad de Granger dada por los CDS para los bonos, y viceversa" (p. 600) | P13: Versão publicada (SciELO Colômbia), p. 583-608.
... A16: 15 | B16: MOSK; PANGALLO; ZEMA (2022) | C16: mosk-2022.md | D16: Relatório (BCE) | E16: Não (relatório) | F16: 2 | G16: Exploratória 2022; contexto P2 | H16: Mostrar que a correlação ações x títulos aumentou recentemente, ligá-la à inflação e discutir efeitos sobre carteiras e estabilidade financeira (Box 2). | I16: EUA (Treasury 10 anos, S&P 500) e zona do euro (Bund 10 anos, EURO STOXX); correlação de 12 meses com dados diários; regressão mensal jan/2000-set/2022 (notas dos Gráficos A e B). | J16: Correlação móvel de 12 meses; MQO robusto com inflação linear e quadrática, VSTOXX e confiança do consumidor, mapeado por sigmoide (Andersson et al., 2008); simulação de carteira. | K16: Correlação positiva do fim dos anos 1960 ao fim dos 1990, negativa nos 2000 e 'has increased recently'. Efeito não linear da inflação, mínimo perto de 2% (zona do euro: α1 = -0,283; α2 = 0,047). VSTOXX alto associado a correlação menor (nota do Gráfico B). | L16: 2022: SUSTENTA EM PARTE (aumento ligado a inflação e aperto monetário; o texto não diz que ficou positiva nem dá o valor). P2: contexto por analogia (VSTOXX). | M16: Janela de 12 meses com dados diários; especificação com inflação² e índice de volatilidade; mínimo da correlação com inflação de ~2%. | N16: Não revisado por pares; coeficientes só da zona do euro; gráficos não lidos; sem Brasil. | O16: "the recent increase in the stock-bond correlation may be related to elevated inflationary pressures and monetary policy tightening." (Box 2) | P16: Página HTML do box (BCE); paginação do PDF do FSR não conferida.

Sheet Matriz
A1: # | B1: Referência | C1: Revisado por pares? | D1: P1 | E1: P2 | F1: P3 | G1: P4 | H1: 2022 (exploratória) | I1: Contexto/lacuna | J1: Método | K1: Observação para a Etapa 2
A2: =Fichamento!A2 | B2: =Fichamento!B2 | C2: =Fichamento!E2 | D2: X | K2: Flight-to-quality nos EUA só em 2 de 6 crises.
A3: =Fichamento!A3 | B3: =Fichamento!B3 | C3: =Fichamento!E3 | D3: X | F3: (X) | K3: P3 só por analogia (EMBI em dólar, FTS global).
A4: =Fichamento!A4 | B4: =Fichamento!B4 | C4: =Fichamento!E4 | D4: (X) | E4: X | K4: Única base direta da P2; não cobre o Brasil.
A5: =Fichamento!A5 | B5: =Fichamento!B5 | C5: =Fichamento!E5 | D5: (X) | E5: (X) | H5: (X) | K5: Explica o sinal pelo regime de inflação, não pelo tipo de choque.
A6: =Fichamento!A6 | B6: =Fichamento!B6 | C6: =Fichamento!E6 | J6: X | K6: Ajuste de viés de volatilidade: robustez e limitação.
A7: =Fichamento!A7 | B7: =Fichamento!B7 | C7: =Fichamento!E7 | D7: (X) | F7: X | I7: C | K7: Brasil com R² 0,01; NÃO serve como fonte para 2022.
A8: =Fichamento!A8 | B8: =Fichamento!B8 | C8: =Fichamento!E8 | F8: (X) | G8: (X) | K8: P4 só indireta; avaliar reformular P4 com CDS > 2%.
A9: =Fichamento!A9 | B9: =Fichamento!B9 | C9: =Fichamento!E9 | F9: X | K9: Justifica o controle pelo câmbio bilateral USD/BRL.
A10: =Fichamento!A10 | B10: =Fichamento!B10 | C10: =Fichamento!E10 | I10: C | K10: Não citar o sinal (ambiguidade taxa x retorno do EMBI).
A11: =Fichamento!A11 | B11: =Fichamento!B11 | C11: =Fichamento!E11 | F11: (X) | I11: X | K11: Anais: não conta como revisado por pares.
A12: =Fichamento!A12 | B12: =Fichamento!B12 | C12: =Fichamento!E12 | I12: C | K12: Reformular a frase da introdução que usa esta obra.
A13: =Fichamento!A13 | B13: =Fichamento!B13 | C13: =Fichamento!E13 | I13: C | K13: Não usar para comovimento ações x títulos.
A14: =Fichamento!A14 | B14: =Fichamento!B14 | C14: =Fichamento!E14 | J14: X | K14: Conferir páginas num exemplar da Bookman 2015.
A15: =Fichamento!A15 | B15: =Fichamento!B15 | C15: =Fichamento!E15 | D15: (X) | E15: X | F15: (X) | K15: Segunda base direta da P2 (EUA); países de risco do euro com correlação positiva.
A16: =Fichamento!A16 | B16: =Fichamento!B16 | C16: =Fichamento!E16 | E16: (X) | H16: X | K16: Fonte para 2022; não diz em texto que a correlação ficou positiva.
B18: Base direta (X) | D18: =COUNTIF(D2:D16,"X") | E18: =COUNTIF(E2:E16,"X") | F18: =COUNTIF(F2:F16,"X") | G18: =COUNTIF(G2:G16,"X") | H18: =COUNTIF(H2:H16,"X")
B19: Base parcial/indireta ((X)) | D19: =COUNTIF(D2:D16,"(X)") | E19: =COUNTIF(E2:E16,"(X)") | F19: =COUNTIF(F2:F16,"(X)") | G19: =COUNTIF(G2:G16,"(X)") | H19: =COUNTIF(H2:H16,"(X)")
B20: Diretas revisadas por pares | D20: =COUNTIFS(D2:D16,"X",$C$2:$C$16,"Sim") | E20: =COUNTIFS(E2:E16,"X",$C$2:$C$16,"Sim") | F20: =COUNTIFS(F2:F16,"X",$C$2:$C$16,"Sim") | G20: =COUNTIFS(G2:G16,"X",$C$2:$C$16,"Sim") | H20: =COUNTIFS(H2:H16,"X",$C$2:$C$16,"Sim")
B21: Situação (critério: ≥ 2 diretas revisadas por pares) | D21: =IF(D20>=2,"OK",IF(D18+D19>=2,"Reforçar","Base fraca")) | E21: =IF(E20>=2,"OK",IF(E18+E19>=2,"Reforçar","Base fraca")) | F21: =IF(F20>=2,"OK",IF(F18+F19>=2,"Reforçar","Base fraca")) | G21: =IF(G20>=2,"OK",IF(G18+G19>=2,"Reforçar","Base fraca")) | H21: =IF(H20>=2,"OK",IF(H18+H19>=2,"Reforçar","Base fraca"))
B22: Critério sugerido no plano de trabalho (Etapa 2, passo 2). '2022' é exploratória e não exige base formal.

Sheet Parâmetros
A1: Parâmetro | B1: Valor / definição | C1: Fonte (pág.) | D1: Uso no artigo (etapa)
A2: Janela da correlação móvel | B2: 63 dias úteis (~1 trimestre); alternativas 21 e 126 | C2: Molenaar et al. (2024, p. 33); Campbell et al. (2017, nota 10, p. 277) | D2: Etapa 4.1 e robustez 4.3
A3: Janela de crise curta | B3: 20 pregões após o evento; referência de 70 dias | C3: Baur e Lucey (2009, p. 346-349) | D3: Robustez; alerta sobre diluição em 63 dias
A4: Horizonte da correlação condicionada ao VIX | B4: 22 pregões (prazo das opções do VIX) | C4: Connolly et al. (2005, p. 3, 16) | D4: P2
A5: Limiar de crise global (VIX) | B5: VIX > 30 (também 20, 25, 35, 40); VIX antigo (S&P 100) | C5: Connolly et al. (2005, Tab. 2, p. 40) | D5: Decisão 3.1; P1, P2, P4
A6: Especificação do teste de P2 | B6: B = a0 + (a1 + a2·ln VIX(t-1))·S; a2 < 0 | C6: Connolly et al. (2005, Eq. 5, p. 18) | D6: P2 (alternativa à regressão da correlação no VIX)
A7: Definição de flight-to-quality | B7: Queda significativa da correlação E nível negativo | C7: Baur e Lucey (2009, p. 341) | D7: Critério de veredito da P1
A8: Definição de flight to safety | B8: Título sobe, ação cai, correlação negativa e estresse | C8: Baele et al. (2020, p. 690) | D8: Revisão de literatura 2.1
A9: FTS global | B9: FTS dos EUA como proxy do choque global | C9: Baele et al. (2020, p. 727) | D9: P4 (crise global)
A10: Dummy de FTS diária | B10: Título > +2 dp e ações < -2 dp | C10: Dufour et al. (2017, p. 18) | D10: Robustez da definição de crise
A11: Limiar de risco soberano | B11: CDS 5 anos > 2% (testado 1% a 3%) | C11: Dufour et al. (2017, p. 13, nota 13) | D11: Possível reformulação da P4
A12: Ajuste de viés de volatilidade | B12: ρ = ρ* / √(1 + δ[1 - ρ*²]); δ = σ²alta/σ²baixa - 1 | C12: Forbes e Rigobon (2002, Eq. 10-11, p. 2233) | D12: Robustez e limitação (4.2)
... A19: Datas de crises fixas | B19: Ásia 01/10-31/12/1997; Rússia 06/07-31/12/1998; Lehman set/2008; subprime ago/2007; soberana europeia jan/2010 | C19: Connolly et al. (2005, p. 19); Bianconi et al. (2013, p. 82); Dufour et al. (2017, p. 10) | D19: Robustez 4.3 (datas da literatura)

Sheet Pendências Etapa 2
A1: # | B1: Pendência | C1: Origem (ficha) | D1: Ação sugerida | E1: Responsável | F1: Status
A2: 1 | B2: P2: parte dos EUA agora com 2 bases diretas (Connolly et al., 2005; Ohmi e Okimoto, 2016); parte do Brasil sem nenhuma | C2: connolly-2005.md; ohmi-2016.md | D2: Buscar estudos de correlação ações x títulos condicionada ao VIX em emergentes; ler Andersson, Krylova e Vähämaa (2008) | F2: Aberta
A3: 2 | B3: Miyajima et al. (2015) não fichado: site do BIS com verificação anti-robô (Gencer, 2015, excluído por falta de acesso) | C3: log-buscas.md (C2, C4) | D3: Um integrante baixa o PDF (bis.org/publ/work391.pdf ou Emerging Markets Review via CAPES) e salva em fichamento/pdfs/ | F3: Aberta
A4: 3 | B4: P4 (crise local x global) sem base direta | C4: dufour-2017.md | D4: Buscar evidência de choque doméstico x global ou reformular P4 com risco soberano elevado (CDS > 2%) | F4: Aberta
A5: 4 | B5: Exploratória 2022: fonte encontrada (Mosk et al., 2022), mas o texto não diz que a correlação ficou positiva | C5: mosk-2022.md | D5: Conferir o Gráfico A do box ou confirmar com os próprios dados na Etapa 4 | F5: Aberta
A6: 5 | B6: Frase da introdução sobre 'natureza do choque' sustentada só em parte | C6: campbell-2017.md | D6: Adotar a redação sugerida na ficha e combinar com Molenaar et al. (2024, p. 20) | F6: Aberta
A7: 6 | B7: Frase antiga sobre Silva et al. (2014) ('Brasil de forma indireta') não se sustenta | C7: silva-2014.md | D7: Reescrever o trecho do eixo 4 na seção 1.3 | F7: Aberta
A8: 7 | B8: Martínez Arroyo e Marín Rodríguez (2021) não tratam de ações | C8: martinez-arroyo-2021.md | D8: Retirar como apoio a comovimento ações x títulos na América Latina | F8: Aberta
A9: 8 | B9: Sinal do EMBI em Bianconi et al. (2013) ambíguo | C9: bianconi-2013.md | D9: Não citar o sinal ou citar o número com a ressalva | F9: Aberta
A10: 9 | B10: Eixo 4 fraco: só uma obra brasileira próxima (Cardoso e Garcia, em anais) | C10: cardoso-2023.md | D10: Busca dirigida em SciELO, RBFin, RBE, EconomiA e anais SBE/ANPEC/SBFin; registrar em log-buscas.md | F10: Aberta
A11: 10 | B11: Páginas de Yin (2015) na edição Bookman não confirmadas | C11: yin-2015.md | D11: Conferir num exemplar físico ou digital | F11: Aberta
A12: 11 | B12: Paginação de Connolly (JFQA), Dufour (JIFMIM) e Hofmann (JMCB) vem de versões preprint/WP | C12: várias | D12: Conferir as páginas citadas na versão publicada antes da redação final | F12: Aberta
A13: 12 | B13: Campo 'Revisado por' sem assinatura humana em todas as fichas | C13: todas | D13: Cada integrante assina conforme a divisão do plano | F13: Aberta

Sheet Legenda
A1: Fichamento resumido | B1: Artigo 'Treasury como porto seguro: Brasil x EUA'. Síntese das 15 fichas em fichamento/*.md: 13 da Etapa 1 e 2 da busca dirigida da Etapa 2 (Ohmi e Okimoto, 2016; Mosk et al., 2022), conferidas em 21 out. 2026. A ficha .md continua sendo a fonte: em caso de dúvida, consultar o arquivo.
A2: Proposições | B2: P1: nos EUA, correlação ações x Treasury negativa em crises de aversão a risco. P2: correlação diminui com o VIX nos EUA, não no Brasil. P3: NTN-B como ativo de risco em crises, mesmo controlando pelo câmbio. P4: efeito mais intenso em crises locais que globais. 2022: exploratória.
A3: X | B3: Sustenta diretamente a proposição.
A4: (X) | B4: Sustenta em parte, por analogia ou de forma indireta.
A5: C | B5: Contexto (sem sustentar uma proposição).
A6: Células amarelas | B6: Para preencher pelo grupo: assinatura 'Revisado por', responsável e status das pendências.
A7: Matriz | B7: Colunas A-C puxam dados da aba Fichamento; as linhas de contagem e a situação são fórmulas e se atualizam ao editar as marcações (lista suspensa X / (X) / C).
A8: Próximo passo | B8: Etapa 2 do plano de trabalho: usar a aba Matriz para gerar fichamento/matriz.md, priorizar as buscas da aba Pendências e registrá-las em fichamento/log-buscas.md.
